{"assets":{"EFA7E3CF1963FE175C942C37E1ED216D":{"type":"texture","index":50,"assetRequest":{"type":"slide","state":"incoming","slide":"808CE764-8414-486A-8596-E36685D687EE"},"url":{"web":"assets/EFA7E3CF1963FE175C942C37E1ED216D.svg"},"width":1024,"height":768},"09A8C11E022CEDC806879AD770A55D4A":{"type":"texture","index":49,"assetRequest":{"type":"slide","state":"outgoing","slide":"D05B9096-FB12-46CE-8B94-0D1FDB6939A3"},"url":{"web":"assets/09A8C11E022CEDC806879AD770A55D4A.svg"},"width":1024,"height":768}},"events":[{"effects":[{"beginTime":0,"baseLayer":{"animations":[],"initialState":{"affineTransform":[1,0,0,1,0,0],"masksToBounds":false,"rotation":0,"scale":1,"position":{"pointX":512,"pointY":384},"width":1024,"sublayerTransform":[1,0,0,0,0,1,0,0,0,0,1,0,0,0,0,1],"contentsRect":{"y":0,"x":0,"width":1,"height":1},"opacity":1,"edgeAntialiasingMask":251658240,"height":768,"hidden":false,"anchorPoint":{"pointX":0.5,"pointY":0.5}},"objectID":"0","layers":[{"animations":[],"initialState":{"affineTransform":[1,0,0,1,0,0],"masksToBounds":false,"rotation":0,"scale":1,"position":{"pointX":512,"pointY":384},"width":1024,"sublayerTransform":[1,0,0,0,0,1,0,0,0,0,1,-0.0004922987690640373,0,0,0,1],"contentsRect":{"y":0,"x":0,"width":1,"height":1},"opacity":1,"edgeAntialiasingMask":251658240,"height":768,"hidden":false,"anchorPoint":{"pointX":0.5,"pointY":0.5}},"layers":[{"animations":[],"layers":[],"initialState":{"affineTransform":[1,0,0,1,0,0],"masksToBounds":false,"rotation":0,"scale":1,"position":{"pointX":512,"pointY":384},"width":1024,"sublayerTransform":[1,0,0,0,0,1,0,0,0,0,1,0,0,0,0,1],"contentsRect":{"y":0,"x":0,"width":1,"height":1},"opacity":1,"edgeAntialiasingMask":0,"height":768,"hidden":false,"anchorPoint":{"pointX":0.5,"pointY":0.5}},"texture":"EFA7E3CF1963FE175C942C37E1ED216D"},{"animations":[{"timeOffset":0,"from":{"scalar":false},"beginTime":0,"repeatCount":0,"fillMode":"both","property":"hidden","autoreverses":false,"duration":0.01,"to":{"scalar":true}}],"layers":[],"initialState":{"affineTransform":[1,0,0,1,0,0],"masksToBounds":false,"rotation":0,"scale":1,"position":{"pointX":512,"pointY":384},"width":1024,"sublayerTransform":[1,0,0,0,0,1,0,0,0,0,1,0,0,0,0,1],"contentsRect":{"y":0,"x":0,"width":1,"height":1},"opacity":1,"edgeAntialiasingMask":0,"height":768,"hidden":false,"anchorPoint":{"pointX":0.5,"pointY":0.5}},"texture":"09A8C11E022CEDC806879AD770A55D4A"}]}]},"effects":[],"duration":0.01,"type":"transition","name":"none","objectID":"0"}],"automaticPlay":false,"hyperlinks":[],"accessibility":[{"text":"code example from FactUI","targetRectangle":{"y":160.92578125,"x":182.6847991943359,"width":658.63037109375,"height":71.36181640625}},{"text":"(f/defquery tasks-for-list","targetRectangle":{"y":303.92578125,"x":29.42967224121094,"width":452.4736328125,"height":35}},{"text":"    \"Find the IDs of all tasks in the given task list\"","targetRectangle":{"y":338.92578125,"x":29.42967224121094,"width":939.7529296875,"height":35}},{"text":"    [:find [?task ...]","targetRectangle":{"y":373.92578125,"x":29.42967224121094,"width":382.8623046875,"height":35}},{"text":"     :in ?tasklist","targetRectangle":{"y":408.92578125,"x":29.42967224121094,"width":313.2509765625,"height":35}},{"text":"     :where","targetRectangle":{"y":443.92578125,"x":29.42967224121094,"width":191.43115234375,"height":35}},{"text":"     [?tasklist :tasklist/tasks ?task]])","targetRectangle":{"y":478.92578125,"x":29.42967224121094,"width":696.11328125,"height":35}}],"baseLayer":{"animations":[],"initialState":{"affineTransform":[1,0,0,1,0,0],"masksToBounds":false,"rotation":0,"scale":1,"position":{"pointX":512,"pointY":384},"width":1024,"sublayerTransform":[1,0,0,0,0,1,0,0,0,0,1,0,0,0,0,1],"contentsRect":{"y":0,"x":0,"width":1,"height":1},"opacity":1,"edgeAntialiasingMask":251658240,"height":768,"hidden":false,"anchorPoint":{"pointX":0.5,"pointY":0.5}},"objectID":"0","layers":[{"animations":[],"initialState":{"affineTransform":[1,0,0,1,0,0],"masksToBounds":false,"rotation":0,"scale":1,"position":{"pointX":512,"pointY":384},"width":1024,"sublayerTransform":[1,0,0,0,0,1,0,0,0,0,1,-0.0004922987690640373,0,0,0,1],"contentsRect":{"y":0,"x":0,"width":1,"height":1},"opacity":1,"edgeAntialiasingMask":251658240,"height":768,"hidden":false,"anchorPoint":{"pointX":0.5,"pointY":0.5}},"layers":[{"animations":[],"layers":[],"initialState":{"affineTransform":[1,0,0,1,0,0],"masksToBounds":false,"rotation":0,"scale":1,"position":{"pointX":512,"pointY":384},"width":1024,"sublayerTransform":[1,0,0,0,0,1,0,0,0,0,1,0,0,0,0,1],"contentsRect":{"y":0,"x":0,"width":1,"height":1},"opacity":1,"edgeAntialiasingMask":0,"height":768,"hidden":false,"anchorPoint":{"pointX":0.5,"pointY":0.5}},"texture":"09A8C11E022CEDC806879AD770A55D4A"}]}]}}]}